fuzzly_configs/__init__.py
fuzzly_configs/api.py
fuzzly_configs/constants.py
fuzzly_configs/models.py
fuzzly_configs-0.0.4.dist-info/LICENSE
fuzzly_configs-0.0.4.dist-info/METADATA
fuzzly_configs-0.0.4.dist-info/WHEEL
fuzzly_configs-0.0.4.dist-info/top_level.txt
fuzzly_configs-0.0.4.dist-info/RECORD
